cpast/__init__.py
cpast/__main__.py
cpast/check.py
cpast/core.py
cpast-0.0.4.dist-info/LICENSE
cpast-0.0.4.dist-info/METADATA
cpast-0.0.4.dist-info/WHEEL
cpast-0.0.4.dist-info/entry_points.txt
cpast-0.0.4.dist-info/top_level.txt
cpast-0.0.4.dist-info/RECORD
