Metadata-Version: 2.1
Name: cpast
Version: 0.0.4
Summary: Git commit in the past
Author-email: skuzow <alex@skuzow.net>
Project-URL: Homepage, https://github.com/skuzow/cpast
Project-URL: Bug Reports, https://github.com/skuzow/cpast/issues
Project-URL: Source, https://github.com/skuzow/cpast
Keywords: git,commit,command,setuptools,development
Classifier: Development Status :: 3 - Alpha
Classifier: Intended Audience :: Developers
Classifier: Topic :: Software Development :: Build Tools
Classifier: License :: OSI Approved :: GNU General Public License v3 (GPLv3)
Classifier: Programming Language :: Python :: 3
Classifier: Programming Language :: Python :: 3.7
Classifier: Programming Language :: Python :: 3.8
Classifier: Programming Language :: Python :: 3.9
Classifier: Programming Language :: Python :: 3.10
Classifier: Programming Language :: Python :: 3.11
Classifier: Programming Language :: Python :: 3 :: Only
Requires-Python: >=3.7
License-File: LICENSE
Provides-Extra: dev
Provides-Extra: test
